routeros_log_exporter/__init__.py
routeros_log_exporter/__main__.py
routeros_log_exporter/_scm_version.py
routeros_log_exporter/cli.py
routeros_log_exporter/exception.py
routeros_log_exporter/fetcher.py
routeros_log_exporter/helper.py
routeros_log_exporter/routeros.py
routeros_log_exporter/output/__init__.py
routeros_log_exporter/output/file.py
routeros_log_exporter/output/format/__init__.py
routeros_log_exporter/output/format/format_json.py
routeros_log_exporter/output/format/format_text.py
routeros_log_exporter-0.2.0.dist-info/LICENSE.md
routeros_log_exporter-0.2.0.dist-info/METADATA
routeros_log_exporter-0.2.0.dist-info/WHEEL
routeros_log_exporter-0.2.0.dist-info/entry_points.txt
routeros_log_exporter-0.2.0.dist-info/top_level.txt
routeros_log_exporter-0.2.0.dist-info/RECORD
