Metadata-Version: 2.1
Name: routeros-log-exporter
Version: 0.2.0
Author: DinoTools
License: ### GNU GENERAL PUBLIC LICENSE
Project-URL: Homepage, https://github.com/DinoTools/routeros-log-exporter
Keywords: RouterOS,MikroTik,logging,exporter
Classifier: Development Status :: 3 - Alpha
Classifier: License :: OSI Approved :: GNU General Public License v3 or later (GPLv3+)
Classifier: Programming Language :: Python
Classifier: Programming Language :: Python :: 3
Requires-Python: >=3.8
License-File: LICENSE.md
Requires-Dist: Click>=8.0.0
Requires-Dist: librouteros>=3.0.0
Requires-Dist: pyyaml>=6.0
